reptile/__init__.py
reptile/reptile.py
reptile/forms/__init__.py
reptile/forms/abstract.py
reptile/forms/checkbox.py
reptile/forms/confirm.py
reptile/forms/input.py
reptile/forms/list.py
reptile/forms/multi.py
reptile-1.0.2.dist-info/LICENSE
reptile-1.0.2.dist-info/METADATA
reptile-1.0.2.dist-info/WHEEL
reptile-1.0.2.dist-info/top_level.txt
reptile-1.0.2.dist-info/RECORD
